mol_eval/commons.py
mol_eval/config.py
mol_eval/data_loader.py
mol_eval/enums.py
mol_eval/eval.py
mol_eval/evaluator.py
mol_eval/logger.py
mol_eval/schemas.py
mol_eval/version.py
mol_eval-0.1.7.dist-info/licenses/LICENSE
mol_eval-0.1.7.dist-info/METADATA
mol_eval-0.1.7.dist-info/WHEEL
mol_eval-0.1.7.dist-info/entry_points.txt
mol_eval-0.1.7.dist-info/top_level.txt
mol_eval-0.1.7.dist-info/RECORD
