Metadata-Version: 2.4
Name: mol_eval
Version: 0.1.7
Summary: A tool for the evaluation of molecules smiles
Author-email: Fabio Bove <fabio.bove.dr@gmail.com>
License:                     GNU GENERAL PUBLIC LICENSE
Project-URL: Homepage, https://github.com/fabiobove-dr/mol_eval
Project-URL: Issues, https://github.com/fabiobove-dr/mol_eval/issues
Keywords: molecule_evaluation,bioinformatics,molecular_similarity
License-File: LICENSE
Requires-Dist: numpy>=2.3.0
Requires-Dist: pandas>=2.3.0
Requires-Dist: tqdm>=4.66.4
Requires-Dist: scipy>=1.15.1
Requires-Dist: rdkit>=2024.9.4
Requires-Dist: Levenshtein>=0.26.0
Requires-Dist: pydantic>=2.11.4
Provides-Extra: test
Requires-Dist: pytest>=7.3.2; extra == "test"
Requires-Dist: pytest-cov>=5.0.0; extra == "test"
Requires-Dist: pytest-mock>=3.14.0; extra == "test"
Requires-Dist: pytest-md>=0.2.0; extra == "test"
Provides-Extra: cuda
Requires-Dist: torch[cuda]==2.3.1; extra == "cuda"
Provides-Extra: cpu
Requires-Dist: torch==2.3.1; extra == "cpu"
Provides-Extra: pre-commit
Requires-Dist: pre-commit>=3.4.0; extra == "pre-commit"
Requires-Dist: black>=23.7.0; extra == "pre-commit"
Requires-Dist: isort>=5.12.0; extra == "pre-commit"
Requires-Dist: flake8>=6.1.0; extra == "pre-commit"
Requires-Dist: mypy>=1.5.0; extra == "pre-commit"
Dynamic: license-file
